{
  "reporters": [
    "default",
    [
      "jest-junit",
      {
        "usePathForSuiteName": "true",
        "classNameTemplate": "[{classname}]",
        "titleTemplate": "{title}",
        "outputDirectory": "test-results/jest",
        "outputName": "./report.xml"
      }
    ]
  ],
  "preset": "ts-jest/presets/default-esm",
  "extensionsToTreatAsEsm": [".ts"],
  "globals": {
    "ts-jest": {
      "useESM": true
    }
  },
  "transform": {
    "^.+\\.tsx?$": "ts-jest"
  },
  "resolver": "<rootDir>/test/resolver.cjs",
  "collectCoverage": true,
  "collectCoverageFrom": ["**/dist/**/*.js", "!**/node_modules/**"],
  "coverageReporters": ["lcov", "text"],
  "coverageDirectory": "coverage",
  "rootDir": "./"
}
